guillotina_hive/__init__.py
guillotina_hive/api.py
guillotina_hive/builtins.py
guillotina_hive/client.py
guillotina_hive/decorators.py
guillotina_hive/exceptions.py
guillotina_hive/install.py
guillotina_hive/interfaces.py
guillotina_hive/permissions.py
guillotina_hive/utils.py
guillotina_hive/commands/__init__.py
guillotina_hive/commands/worker.py
guillotina_hive/content/__init__.py
guillotina_hive/content/deque_folder.py
guillotina_hive/content/dist_task.py
guillotina_hive/content/execution.py
guillotina_hive/content/hive_folder.py
guillotina_hive/content/task.py
guillotina_hive/model/__init__.py
guillotina_hive/model/task.py
guillotina_hive/tests/__init__.py
guillotina_hive/tests/conftest.py
guillotina_hive/tests/fixtures.py
guillotina_hive/tests/tasks.py
guillotina_hive/tests/test_apply_recursive.py
guillotina_hive/tests/test_dequefolder.py
guillotina_hive/tests/test_es.py
guillotina_hive/tests/test_hive.py
guillotina_hive/tests/test_task.py
guillotina_hive/tests/test_worker.py
guillotina_hive/tests/utils.py
guillotina_hive-1.0.15.dist-info/METADATA
guillotina_hive-1.0.15.dist-info/RECORD
guillotina_hive-1.0.15.dist-info/WHEEL
guillotina_hive-1.0.15.dist-info/top_level.txt
guillotina_hive-1.0.15.dist-info/zip-safe
