Metadata-Version: 2.1
Name: guillotina-hive
Version: 1.0.15
Summary: Guillotina addon to split actions into smaller bits
Home-page: https://github.com/onna/guillotina_hive
Author: Ramon Navarro & Nathan VanGheem
Author-email: ramon@onna.com
License: BSD
Keywords: asyncio,REST,Framework,transactional
Platform: UNKNOWN
Classifier: License :: OSI Approved :: BSD License
Classifier: Development Status :: 3 - Alpha
Classifier: Intended Audience :: Developers
Classifier: Topic :: Internet :: WWW/HTTP
Classifier: Programming Language :: Python :: 3.6
Classifier: Topic :: Software Development :: Libraries :: Python Modules
Provides-Extra: test
Requires-Dist: setuptools
Requires-Dist: guillotina (>=2.1.0)
Requires-Dist: async-timeout
Requires-Dist: aioclustermanager
Requires-Dist: psycopg2
Provides-Extra: test
Requires-Dist: pytest; extra == 'test'
Requires-Dist: docker; extra == 'test'
Requires-Dist: backoff; extra == 'test'
Requires-Dist: pytest-asyncio; extra == 'test'
Requires-Dist: pytest-aiohttp; extra == 'test'
Requires-Dist: pytest-cov; extra == 'test'
Requires-Dist: pytest-docker-fixtures; extra == 'test'
Requires-Dist: guillotina-elasticsearch; extra == 'test'
